aioiotprov/__init__.py
aioiotprov/__main__.py
aioiotprov/aioiotprov.py
aioiotprov/plugins/broadlink.py
aioiotprov/plugins/etrix.py
aioiotprov/plugins/shelly.py
aioiotprov/plugins/tasmota.py
aioiotprov/plugins/tp-link.py
aioiotprov/plugins/yeelight.py
aioiotprov-0.0.8.dist-info/LICENSE
aioiotprov-0.0.8.dist-info/METADATA
aioiotprov-0.0.8.dist-info/WHEEL
aioiotprov-0.0.8.dist-info/entry_points.txt
aioiotprov-0.0.8.dist-info/top_level.txt
aioiotprov-0.0.8.dist-info/RECORD
