Metadata-Version: 2.1
Name: aioiotprov
Version: 0.0.8
Summary: Library/utility to help provision various IoT devices.
Home-page: http://github.com/frawau/aioiotprov
Author: François Wautier
Author-email: francois@wautier.eu
License: MIT
Keywords: IoT,provisioning,automation
Platform: UNKNOWN
Classifier: License :: OSI Approved :: MIT License
Classifier: Programming Language :: Python :: 3
Classifier: Programming Language :: Python :: 3.5
Requires-Dist: aiohttp
